odoo8_addon_web_invalid_tab-8.0.1.0.0.99.dev3-py2.7-nspkg.pth
odoo8_addon_web_invalid_tab-8.0.1.0.0.99.dev3.dist-info/METADATA
odoo8_addon_web_invalid_tab-8.0.1.0.0.99.dev3.dist-info/RECORD
odoo8_addon_web_invalid_tab-8.0.1.0.0.99.dev3.dist-info/WHEEL
odoo8_addon_web_invalid_tab-8.0.1.0.0.99.dev3.dist-info/namespace_packages.txt
odoo8_addon_web_invalid_tab-8.0.1.0.0.99.dev3.dist-info/top_level.txt
odoo_addons/web_invalid_tab/README.rst
odoo_addons/web_invalid_tab/__init__.py
odoo_addons/web_invalid_tab/__openerp__.py
odoo_addons/web_invalid_tab/i18n/web_invalid_tab.pot
odoo_addons/web_invalid_tab/static/description/icon.png
odoo_addons/web_invalid_tab/static/src/css/view_form.css
odoo_addons/web_invalid_tab/static/src/js/view_form.js
odoo_addons/web_invalid_tab/views/assets.xml
